{"1610060958566862848": {"tweet_id": "1610060958566862848", "username": "litecoin", "name": "Litecoin", "profile_picture": "https://pbs.twimg.com/profile_images/1377788667691855872/LrysCc5Q_normal.jpg", "replies": 42, "retweets": 132, "likes": 676, "is_retweet": false, "posted_time": "2023-01-02T23:50:20+00:00", "content": "In just one year, monthly Litecoin use, with the worlds largest crypto processor, increased 109% ", "hashtags": [], "mentions": [], "images": ["https://pbs.twimg.com/media/FlgVlLuagAE01AS?format=jpg&name=small"], "videos": [], "tweet_url": "https://twitter.com/litecoin/status/1610060958566862848", "link": ""}, "1610060682115915777": {"tweet_id": "1610060682115915777", "username": "greg16676935420", "name": "greg", "profile_picture": "https://pbs.twimg.com/profile_images/1581014308397502464/NPogKMyk_normal.jpg", "replies": 58, "retweets": 78, "likes": 3393, "is_retweet": false, "posted_time": "2023-01-02T23:49:14+00:00", "content": "Jim predicting a bad year for crypto makes me so bullish", "hashtags": [], "mentions": [], "images": [], "videos": [], "tweet_url": "https://twitter.com/greg16676935420/status/1610060682115915777", "link": ""}, "1610060125296889858": {"tweet_id": "1610060125296889858", "username": "jimcramer", "name": "Jim Cramer", "profile_picture": "https://pbs.twimg.com/profile_images/1461426655046606860/PzlSk4fZ_normal.jpg", "replies": 2950, "retweets": 1487, "likes": 4924, "is_retweet": false, "posted_time": "2023-01-02T23:47:01+00:00", "content": "As i predict another weak year for crypto, i do ponder how many people are still involved, now many millions of people....", "hashtags": [], "mentions": [], "images": [], "videos": [], "tweet_url": "https://twitter.com/jimcramer/status/1610060125296889858", "link": ""}, "1610050787748773888": {"tweet_id": "1610050787748773888", "username": "CroissantEth", "name": ".eth", "profile_picture": "https://pbs.twimg.com/profile_images/1522869770835697664/vppFIJfi_normal.jpg", "replies": 26, "retweets": 149, "likes": 509, "is_retweet": false, "posted_time": "2023-01-02T23:09:55+00:00", "content": "The abrupt formation of different narratives in crypto never ceases to amaze me.\n\nThere is almost always a constant flow of ideas where the \ud835\ude33\ud835\ude26\ud835\ude22\ud835\ude2d \ud835\ude2e\ud835\ude30\ud835\ude2f\ud835\ude26\ud835\ude3a is made.\n\nLet\u2019s analyze this from a historical perspective\u2026", "hashtags": [], "mentions": [], "images": [], "videos": [], "tweet_url": "https://twitter.com/CroissantEth/status/1610050787748773888", "link": ""}, "1610049600106237952": {"tweet_id": "1610049600106237952", "username": "kattenbarge", "name": "Kat Tenbarge", "profile_picture": "https://pbs.twimg.com/profile_images/1410586701848891392/_94M4pBd_normal.jpg", "replies": 73, "retweets": 234, "likes": 2085, "is_retweet": false, "posted_time": "2023-01-02T23:05:12+00:00", "content": "I\u2019ve already seen plenty of Andrew Tate fans and allies in the crypto/influencing space say the investigation into him is \u201cbiased\u201d and \u201cunfair.\u201d If he\u2019s found guilty, they\u2019ve already primed themselves and their audiences to believe he\u2019s innocent no matter what.", "hashtags": [], "mentions": [], "images": [], "videos": [], "tweet_url": "https://twitter.com/kattenbarge/status/1610049600106237952", "link": ""}, "1610046405388664834": {"tweet_id": "1610046405388664834", "username": "intocryptoverse", "name": "Benjamin Cowen", "profile_picture": "https://pbs.twimg.com/profile_images/1393293173854597120/t-KVh409_normal.jpg", "replies": 139, "retweets": 326, "likes": 3296, "is_retweet": false, "posted_time": "2023-01-02T22:52:30+00:00", "content": "Onto another year for crypto\u2026", "hashtags": [], "mentions": [], "images": ["https://pbs.twimg.com/media/FlgIq-rXEAABgBJ?format=jpg&name=small"], "videos": [], "tweet_url": "https://twitter.com/intocryptoverse/status/1610046405388664834", "link": ""}, "1610033442405720065": {"tweet_id": "1610033442405720065", "username": "unusual_whales", "name": "unusual_whales", "profile_picture": "https://pbs.twimg.com/profile_images/1610160756292743172/aMthseAB_normal.png", "replies": 960, "retweets": 552, "likes": 2932, "is_retweet": false, "posted_time": "2023-01-02T22:01:00+00:00", "content": "Jim Cramer has said: \"I would not touch crypto in a million years.\"", "hashtags": [], "mentions": [], "images": ["https://pbs.twimg.com/ext_tw_video_thumb/1609049390798475264/pu/img/W2bG1CHxtD6mDKoN.jpg"], "videos": ["blob:https://twitter.com/96c6db26-cc4b-41da-8834-79ee141a6536"], "tweet_url": "https://twitter.com/unusual_whales/status/1610033442405720065", "link": ""}}