{"1491199408691900416": {"tweet_id": "1491199408691900416", "username": "XRP_Productions", "name": "XRPP", "profile_picture": "https://pbs.twimg.com/profile_images/1606711648579993602/Ps08jpUV_normal.jpg", "replies": 45, "retweets": 65, "likes": 758, "is_retweet": false, "posted_time": "2022-02-08T23:56:58+00:00", "content": "Did anyone else notice the effect that \n@BCBacker\n had on \n@Bitboy_Crypto\n today?\n\n#XRP #XRPtheStandard", "hashtags": ["XRP", "XRPtheStandard"], "mentions": ["BCBacker", "Bitboy_Crypto"], "images": ["https://pbs.twimg.com/media/FLHN0faVUAEFdg2?format=jpg&name=small"], "videos": [], "tweet_url": "https://twitter.com/XRP_Productions/status/1491199408691900416", "link": ""}, "1491198154867462149": {"tweet_id": "1491198154867462149", "username": "tante", "name": "tante", "profile_picture": "https://pbs.twimg.com/profile_images/1273617971546554371/GBFic03W_normal.jpg", "replies": 5, "retweets": 30, "likes": 180, "is_retweet": false, "posted_time": "2022-02-08T23:51:59+00:00", "content": "If you've looked at the crypto space for a while \"cringe rapper and y-combinator nerd  crypto robber queen and baron\" feels like just another normal Wednesday.", "hashtags": [], "mentions": [], "images": [], "videos": [], "tweet_url": "https://twitter.com/tante/status/1491198154867462149", "link": ""}, "1491197546110517248": {"tweet_id": "1491197546110517248", "username": "JackNiewold", "name": "Jack Niewold", "profile_picture": "https://pbs.twimg.com/profile_images/1558175102835073025/UnhjcE8T_normal.jpg", "replies": 20, "retweets": 88, "likes": 893, "is_retweet": false, "posted_time": "2022-02-08T23:49:34+00:00", "content": "It's a good reminder that exchanges aren't 100% safe, that $BTC isn't private, and that you should store your keys offline.\n\nAn insane saga. Another day in crypto.", "hashtags": [], "mentions": [], "images": [], "videos": [], "tweet_url": "https://twitter.com/JackNiewold/status/1491197546110517248", "link": ""}, "1491197430842654721": {"tweet_id": "1491197430842654721", "username": "JackNiewold", "name": "Jack Niewold", "profile_picture": "https://pbs.twimg.com/profile_images/1558175102835073025/UnhjcE8T_normal.jpg", "replies": 7, "retweets": 26, "likes": 474, "is_retweet": false, "posted_time": "2022-02-08T23:49:07+00:00", "content": "Also, now the federal government has nearly $4 billion in crypto on their balance sheet. \n\nYeah, it's not technically 'theirs.'\n\nBut on the other hand, it kind of is. It also shows us that the DOJ is both closely examining and deploying massive resources to the crypto industry.", "hashtags": [], "mentions": [], "images": [], "videos": [], "tweet_url": "https://twitter.com/JackNiewold/status/1491197430842654721", "link": ""}, "1491197016931987457": {"tweet_id": "1491197016931987457", "username": "EdgeofSports", "name": "Dave Zirin", "profile_picture": "https://pbs.twimg.com/profile_images/851537604763844608/dvkHePUa_normal.jpg", "replies": 31, "retweets": 48, "likes": 296, "is_retweet": false, "posted_time": "2022-02-08T23:47:28+00:00", "content": "How many Super Bowl commercials will be about products that are actually manufactured and how many will be some variant of picking the last meat off the bones of the US economy? (Gambling, crypto etc) I\u2019m going to keep track. Should be a fun Super Bowl party! ", "hashtags": [], "mentions": [], "images": [], "videos": [], "tweet_url": "https://twitter.com/EdgeofSports/status/1491197016931987457", "link": ""}, "1491196955246362629": {"tweet_id": "1491196955246362629", "username": "CosmoJenkinz", "name": "JENKINZ", "profile_picture": "https://pbs.twimg.com/profile_images/1611486882885521416/iMpXWYpq_normal.jpg", "replies": 11, "retweets": 2, "likes": 168, "is_retweet": false, "posted_time": "2022-02-08T23:47:13+00:00", "content": "Things don\u2019t need to make sense to make  in crypto", "hashtags": [], "mentions": [], "images": [], "videos": [], "tweet_url": "https://twitter.com/CosmoJenkinz/status/1491196955246362629", "link": ""}, "1491196330370568192": {"tweet_id": "1491196330370568192", "username": "dobby__isfree", "name": "dobbyisfree.eth", "profile_picture": "https://pbs.twimg.com/profile_images/1528023747923435520/VcwTkPh2_normal.jpg", "replies": 39, "retweets": 20, "likes": 320, "is_retweet": false, "posted_time": "2022-02-08T23:44:44+00:00", "content": "I just got my second \n@Crypto__Chicks\n !!\nreally love this collection, where is my fam? ", "hashtags": [], "mentions": ["Crypto__Chicks"], "images": ["https://pbs.twimg.com/media/FLHLAUqXwAQ5tZF?format=jpg&name=small"], "videos": [], "tweet_url": "https://twitter.com/dobby__isfree/status/1491196330370568192", "link": ""}}