{"1482133096354959364": {"tweet_id": "1482133096354959364", "username": "Cryptobolix", "name": "Cryptobolix", "profile_picture": "https://pbs.twimg.com/profile_images/1553754166811656193/-aYmKlox_normal.jpg", "replies": 71, "retweets": 122, "likes": 447, "is_retweet": false, "posted_time": "2022-01-14T23:30:41+00:00", "content": "I see a lot of negative talk about #Saitama today. This stuff happens in #Crypto. It can feel unpleasant.\nThe one thing I did today, was I bought this amazing dip. \n\nI just increased my position like you wouldn\u2019t believe. Extremely happy with #SaitamaWolfPack and their strength!", "hashtags": ["Saitama", "Crypto", "SaitamaWolfPack"], "mentions": [], "images": [], "videos": [], "tweet_url": "https://twitter.com/Cryptobolix/status/1482133096354959364", "link": ""}, "1482131550116487168": {"tweet_id": "1482131550116487168", "username": "StevenBartlett", "name": "Steven Bartlett", "profile_picture": "https://pbs.twimg.com/profile_images/1472223883847741450/WPD03FTB_normal.jpg", "replies": 121, "retweets": 107, "likes": 453, "is_retweet": false, "posted_time": "2022-01-14T23:24:32+00:00", "content": "I\u2019m now the proud owner of quite a few  \n@Crypto_Skulls\n!\n\nExtra bullish on this project. \n\nWho else is in?\n\n#CryptoSkulls", "hashtags": ["CryptoSkulls"], "mentions": ["Crypto_Skulls"], "images": ["https://pbs.twimg.com/media/FJGVemvWYAkY8G_?format=jpg&name=small"], "videos": [], "tweet_url": "https://twitter.com/StevenBartlett/status/1482131550116487168", "link": ""}, "1482131512006950916": {"tweet_id": "1482131512006950916", "username": "coachdeesmith", "name": "Deerick Smith", "profile_picture": "https://pbs.twimg.com/profile_images/1595196149568360453/zpGJttZz_normal.jpg", "replies": 13, "retweets": 6, "likes": 142, "is_retweet": false, "posted_time": "2022-01-14T23:24:23+00:00", "content": "Eat on a cutting board, buy crypto, take ice baths, drink bone broth, take cold showers and you will retire within 24 hours", "hashtags": [], "mentions": [], "images": [], "videos": [], "tweet_url": "https://twitter.com/coachdeesmith/status/1482131512006950916", "link": ""}, "1482127341283389444": {"tweet_id": "1482127341283389444", "username": "evgenymorozov", "name": "Evgeny Morozov", "profile_picture": "https://pbs.twimg.com/profile_images/1339141856345600000/R2J48kha_normal.jpg", "replies": 9, "retweets": 61, "likes": 307, "is_retweet": false, "posted_time": "2022-01-14T23:07:49+00:00", "content": "\"Crypto-economics\": \n1. Take the weirdest parts of microeconomics, with the most problematic assumptions about agency (game theory, mechanism design) \n2. Remove ANY (even orthodox) macroeconomics \n3. Insert weird localist /free banking critiques of fiat money\n4. Shake and enjoy!", "hashtags": [], "mentions": [], "images": [], "videos": [], "tweet_url": "https://twitter.com/evgenymorozov/status/1482127341283389444", "link": ""}, "1482125752279597056": {"tweet_id": "1482125752279597056", "username": "3LUENFT", "name": "3LUE", "profile_picture": "https://pbs.twimg.com/profile_images/1618650388785242113/c74v5_-m_normal.png", "replies": 43, "retweets": 124, "likes": 340, "is_retweet": false, "posted_time": "2022-01-14T23:01:30+00:00", "content": "POP UP \n@Crypto_Skulls\n SPACES IN 30 MINUTES. Come chat some history with me and \n@LeonidasNFT\n ", "hashtags": [], "mentions": ["Crypto_Skulls", "LeonidasNFT"], "images": [], "videos": [], "tweet_url": "https://twitter.com/3LUENFT/status/1482125752279597056", "link": ""}, "1482123490216103937": {"tweet_id": "1482123490216103937", "username": "nfttank", "name": "Tank", "profile_picture": "https://pbs.twimg.com/profile_images/1615395702804185100/LNgzvjKU_normal.jpg", "replies": 58, "retweets": 97, "likes": 378, "is_retweet": false, "posted_time": "2022-01-14T22:52:31+00:00", "content": "How could I miss Bitcoin?\nHow could I miss Ethereum?\nHow could I miss CryptoPunks?\nI don't want to ask myself how I could miss \n@Crypto_Skulls\n next year.", "hashtags": [], "mentions": ["Crypto_Skulls"], "images": ["https://pbs.twimg.com/media/FJGLIGlX0AIMCxm?format=png&name=360x360", "https://pbs.twimg.com/media/FJGLKbQX0AUBGqG?format=png&name=360x360"], "videos": [], "tweet_url": "https://twitter.com/nfttank/status/1482123490216103937", "link": ""}, "1482123203178684419": {"tweet_id": "1482123203178684419", "username": "AltcoinDailyio", "name": "Altcoin Daily", "profile_picture": "https://pbs.twimg.com/profile_images/1477451940611035136/hQByG8MW_normal.png", "replies": 168, "retweets": 58, "likes": 352, "is_retweet": false, "posted_time": "2022-01-14T22:51:22+00:00", "content": "BIGGEST MOMENT FOR #CRYPTO HAPPENING NOW! \n@TESLA\n ACCEPTS #DOGECOIN!\n\nPOLYGON $MATIC EIP-1559 UPGRADE NEXT WEEK\n@Fidelity\n's MEGA-BULLISH #Bitcoin Report\n\nWATCH NOW \n>> https://youtu.be/vTKxj_fo8mk", "hashtags": ["CRYPTO", "DOGECOIN", "Bitcoin"], "mentions": ["TESLA", "Fidelity"], "images": ["https://pbs.twimg.com/media/FJGPHjGVEAIvvqk?format=jpg&name=small"], "videos": [], "tweet_url": "https://twitter.com/AltcoinDailyio/status/1482123203178684419", "link": ""}}