{"1437566654360309760": {"tweet_id": "1437566654360309760", "username": "sptroy", "name": "Stephen Troy", "profile_picture": "https://pbs.twimg.com/profile_images/451152346471354368/bFew1Gji_normal.jpeg", "replies": 12, "retweets": 30, "likes": 151, "is_retweet": false, "posted_time": "2021-09-13T23:59:33+00:00", "content": "I\u2019ve seen this on crypto Twitter and it\u2019s false. It\u2019s related to 1099s and there is already a $600 reporting minimum. The only new thing is it applies to employers paying in crypto.", "hashtags": [], "mentions": [], "images": [], "videos": [], "tweet_url": "https://twitter.com/sptroy/status/1437566654360309760", "link": ""}, "1437566185273503744": {"tweet_id": "1437566185273503744", "username": "DidIDoThatRight", "name": "Freebird \u24e3", "profile_picture": "https://pbs.twimg.com/profile_images/1621733373013000192/x5CogUhr_normal.jpg", "replies": 30, "retweets": 12, "likes": 276, "is_retweet": false, "posted_time": "2021-09-13T23:57:41+00:00", "content": "I don\u2019t need a Lambo in the garage.  \nI certainly don\u2019t need a flashy watch on my wrist. And I could care less about having a million followers on Twitter. \n\nI\u2019m in crypto for one reason and one reason only: To protect the treasure I already have at home. \n\n$BTC $ETH $TEL $ADA", "hashtags": [], "mentions": [], "images": ["https://pbs.twimg.com/media/E_NC03UXIAsw5Gk?format=jpg&name=small"], "videos": [], "tweet_url": "https://twitter.com/DidIDoThatRight/status/1437566185273503744", "link": ""}, "1437565882784419841": {"tweet_id": "1437565882784419841", "username": "healthy_pockets", "name": "Healthy Pockets", "profile_picture": "https://pbs.twimg.com/profile_images/1536452233755254785/leeJHYvY_normal.jpg", "replies": 37, "retweets": 57, "likes": 678, "is_retweet": false, "posted_time": "2021-09-13T23:56:29+00:00", "content": ".#Polkadot ha logrado adelantar a #doge para situarse como la 8\u00aa #Crypto con mayor capitalizaci\u00f3n de mercado seg\u00fan el ranking de \n@CoinMarketCap\n ", "hashtags": ["Polkadot", "doge", "Crypto"], "mentions": ["CoinMarketCap"], "images": ["https://pbs.twimg.com/media/E_NCErsWYAUfo96?format=png&name=small"], "videos": [], "tweet_url": "https://twitter.com/healthy_pockets/status/1437565882784419841", "link": ""}, "1437561835948060673": {"tweet_id": "1437561835948060673", "username": "IOV_OWL", "name": "King Solomon", "profile_picture": "https://pbs.twimg.com/profile_images/1598003435340693518/sHjAiAtj_normal.jpg", "replies": 52, "retweets": 157, "likes": 1111, "is_retweet": false, "posted_time": "2021-09-13T23:40:24+00:00", "content": "If you believe XRP is a shitcoin I\u2019m assuming you believe:\n\n- The government is here to help you\n- Bitcoin is revolutionizing anything in 2021 \n- Your meme coin will survive a bear market \n- Ethereum gas fees are good for crypto \n- Crypto replaces digital fiat", "hashtags": [], "mentions": [], "images": [], "videos": [], "tweet_url": "https://twitter.com/IOV_OWL/status/1437561835948060673", "link": ""}, "1437559070513410049": {"tweet_id": "1437559070513410049", "username": "loomdart", "name": "loomdart.lens - no eggs arc", "profile_picture": "https://pbs.twimg.com/profile_images/1607974005499207680/Y9YgWMPw_normal.jpg", "replies": 37, "retweets": 18, "likes": 197, "is_retweet": true, "posted_time": "2021-09-13T23:29:25+00:00", "content": "You ask for pump it loomdart well you don't get pump it loomdart you get PUMP IT LOOMDART AT HOME\n\nAnyways we are finally out and im happy to announce I'm a cofounder of \n@metadropmeta\n go read below and get ready for \n@loomlocknft\n the coolest crypto project ever", "hashtags": [], "mentions": ["metadropmeta", "loomlocknft"], "images": ["https://pbs.twimg.com/ext_tw_video_thumb/1437553608279695362/pu/img/w5jYi378qHHf4mDl.jpg"], "videos": ["blob:https://twitter.com/c2d57e91-110e-4bfd-a252-dd1004b02965"], "tweet_url": "https://twitter.com/loomdart/status/1437559070513410049", "link": ""}}