{"1523815039223873537": {"tweet_id": "1523815039223873537", "username": "divine_economy", "name": "david phelps", "profile_picture": "https://pbs.twimg.com/profile_images/1496705014177411077/TT3vu4m8_normal.jpg", "replies": 5, "retweets": 1, "likes": 60, "is_retweet": false, "posted_time": "2022-05-09T23:59:51+00:00", "content": "not saying i *necessarily* believe this, but there\u2019s a case that in the crypto euphoria of 21-22, apes showed us everything wrong with nfts, daos, defi, data, and L1s", "hashtags": [], "mentions": [], "images": [], "videos": [], "tweet_url": "https://twitter.com/divine_economy/status/1523815039223873537", "link": ""}, "1523815038439632897": {"tweet_id": "1523815038439632897", "username": "5TimesDistilled", "name": "5TimesDistilled.eth", "profile_picture": "https://pbs.twimg.com/profile_images/1532945868965482497/nj6LYK4h_normal.jpg", "replies": 8, "retweets": 3, "likes": 59, "is_retweet": false, "posted_time": "2022-05-09T23:59:50+00:00", "content": "The only thing receding faster than the crypto markets rn is my hairline ", "hashtags": [], "mentions": [], "images": [], "videos": [], "tweet_url": "https://twitter.com/5TimesDistilled/status/1523815038439632897", "link": ""}, "1523814852912766976": {"tweet_id": "1523814852912766976", "username": "GerberKawasaki", "name": "Ross Gerber", "profile_picture": "https://pbs.twimg.com/profile_images/1384991896267739137/W3r3njew_normal.jpg", "replies": 26, "retweets": 6, "likes": 108, "is_retweet": false, "posted_time": "2022-05-09T23:59:06+00:00", "content": "Same with bitcoin. The goal is to covert cash to Crypto at the best exchange rate possible if you plan on keeping it forever. You get paid in cash with inflation. Covert to bitcoin. You get more bitcoin when it goes down. ", "hashtags": [], "mentions": [], "images": [], "videos": [], "tweet_url": "https://twitter.com/GerberKawasaki/status/1523814852912766976", "link": ""}, "1523814755613708288": {"tweet_id": "1523814755613708288", "username": "Web3Familia", "name": "Web3 Familia", "profile_picture": "https://pbs.twimg.com/profile_images/1569312547198607361/o4FvNHCj_normal.jpg", "replies": 4, "retweets": 1, "likes": 24, "is_retweet": false, "posted_time": "2022-05-09T23:58:43+00:00", "content": "Hey Shai  We're happy to chat anytime! Would also recommend checking out other amazing Latino-led projects like \n@Latinoverse_\n @latino_society\n @crypto_mujeres\n @holametaverso\n @nftenespanol\n ", "hashtags": [], "mentions": ["Latinoverse_", "latino_society", "crypto_mujeres", "holametaverso", "nftenespanol"], "images": [], "videos": [], "tweet_url": "https://twitter.com/Web3Familia/status/1523814755613708288", "link": ""}, "1523814673992208384": {"tweet_id": "1523814673992208384", "username": "JddarthEnter", "name": "JD | enter", "profile_picture": "https://pbs.twimg.com/profile_images/1463442780991094784/6-bUDacQ_normal.jpg", "replies": 0, "retweets": 4, "likes": 16, "is_retweet": false, "posted_time": "2022-05-09T23:58:24+00:00", "content": "Weekly Update week #31\n\nhttp://Enter.market Launch Eta\n\nNFTART/BNB Farm on http://dibs.money\n\nFra krypto til kunst/ From crypto to art conference \n\nXP system on Discord\n\n#EnterNFT #EnterArmy #EnterArt", "hashtags": ["31", "EnterNFT", "EnterArmy", "EnterArt"], "mentions": [], "images": ["https://pbs.twimg.com/media/FSWtDP0VgAAqaD6?format=jpg&name=small"], "videos": [], "tweet_url": "https://twitter.com/JddarthEnter/status/1523814673992208384", "link": ""}, "1523814563266899968": {"tweet_id": "1523814563266899968", "username": "davidgokhshtein", "name": "David Gokhshtein", "profile_picture": "https://pbs.twimg.com/profile_images/1615577395196575745/7nrDNd28_normal.jpg", "replies": 104, "retweets": 4, "likes": 25, "is_retweet": false, "posted_time": "2022-05-09T23:57:57+00:00", "content": "Join me in my Space! #crypto #bitcoin", "hashtags": ["crypto", "bitcoin"], "mentions": [], "images": [], "videos": [], "tweet_url": "https://twitter.com/davidgokhshtein/status/1523814563266899968", "link": ""}, "1523814536683433984": {"tweet_id": "1523814536683433984", "username": "cryptojourney77", "name": "\u2102\ud835\udd63\ud835\udd6a\ud835\udd61\ud835\udd65\u00f8\ud835\ude79\ud835\ude98\ud835\ude9e\ud835\ude9b\ud835\ude97\ud835\ude8e\ud835\udea2", "profile_picture": "https://pbs.twimg.com/profile_images/1524481188727042049/tZnU3MTU_normal.jpg", "replies": 1, "retweets": 2, "likes": 12, "is_retweet": false, "posted_time": "2022-05-09T23:57:51+00:00", "content": "Poignant article by a true OG \n@SaschaBailey\n on art NFTs today and how things have changed. His platform \n@Blockchainartex\n played an instrumental role in my appreciating the pure discovery of original crypto art 2 years ago", "hashtags": [], "mentions": ["SaschaBailey", "Blockchainartex"], "images": [], "videos": [], "tweet_url": "https://twitter.com/cryptojourney77/status/1523814536683433984", "link": "https://t.co/XWrpId46rF"}}