{"1564398710909415425": {"tweet_id": "1564398710909415425", "username": "EricRWeinstein", "name": "Eric Weinstein", "profile_picture": "https://pbs.twimg.com/profile_images/1405314351486144519/Uage5phF_normal.jpg", "replies": 109, "retweets": 50, "likes": 514, "is_retweet": false, "posted_time": "2022-08-29T23:44:52+00:00", "content": "How do we delink our conversations about crypto as technology from wealth? Blockchains don\u2019t get less interesting as technology when USD exchange rates go down. Why violently oscillate between laughing at Crypto when it\u2019s down & maximal abuse from Maximalists when up? So dumb. ", "hashtags": [], "mentions": [], "images": [], "videos": [], "tweet_url": "https://twitter.com/EricRWeinstein/status/1564398710909415425", "link": ""}, "1564393461167656961": {"tweet_id": "1564393461167656961", "username": "healthy_pockets", "name": "Healthy Pockets", "profile_picture": "https://pbs.twimg.com/profile_images/1536452233755254785/leeJHYvY_normal.jpg", "replies": 33, "retweets": 82, "likes": 685, "is_retweet": false, "posted_time": "2022-08-29T23:24:00+00:00", "content": "Empresario hondure\u00f1o  aceptando #Bitcoin como medio de pago en su puesto de Granizados \n\n#Crypto #btc", "hashtags": ["Bitcoin", "Crypto", "btc"], "mentions": [], "images": ["https://pbs.twimg.com/media/FbXXjtiXkAEjR5n?format=jpg&name=small"], "videos": [], "tweet_url": "https://twitter.com/healthy_pockets/status/1564393461167656961", "link": ""}, "1564393406171754496": {"tweet_id": "1564393406171754496", "username": "pythianism", "name": "Vance Spencer", "profile_picture": "https://pbs.twimg.com/profile_images/1623028953706557440/aiczcJho_normal.jpg", "replies": 88, "retweets": 79, "likes": 610, "is_retweet": false, "posted_time": "2022-08-29T23:23:47+00:00", "content": "we really only need 1 crypto game to work and show the rest the way\n\nonce we know the path the consensus will rapidly converge and you get the virtuous flywheel of vcs funding and an order of magnitude more games building\n\nsame thing happened with defi - \u201ccompound moment\u201d", "hashtags": [], "mentions": [], "images": [], "videos": [], "tweet_url": "https://twitter.com/pythianism/status/1564393406171754496", "link": ""}, "1564393224180989952": {"tweet_id": "1564393224180989952", "username": "WifeyAlpha", "name": "Wifey", "profile_picture": "https://pbs.twimg.com/profile_images/1620236289197883393/Ocb1dH3B_normal.jpg", "replies": 9, "retweets": 4, "likes": 228, "is_retweet": false, "posted_time": "2022-08-29T23:23:04+00:00", "content": "This account \n@alCamel77\n is private so maybe he will be angry at me for shoutout but he has the best memes (I  steal a lot of them from him - don\u2019t tell him). He is in crypto circles I respect greatly and seen solid tweets on market action from him. Credit where due. Follow him.", "hashtags": [], "mentions": ["alCamel77"], "images": [], "videos": [], "tweet_url": "https://twitter.com/WifeyAlpha/status/1564393224180989952", "link": ""}, "1564391386857803778": {"tweet_id": "1564391386857803778", "username": "alancarroII", "name": "Alan Carroll", "profile_picture": "https://pbs.twimg.com/profile_images/1517860960085630977/3C50Zy3N_normal.jpg", "replies": 21, "retweets": 92, "likes": 350, "is_retweet": false, "posted_time": "2022-08-29T23:15:46+00:00", "content": "\u201cThe crypto market isn\u2019t THAT volatile\u201d\n\nThe crypto market:", "hashtags": [], "mentions": [], "images": ["https://pbs.twimg.com/ext_tw_video_thumb/1564391328498196482/pu/img/NWsjPBHYBBlbW7m-.jpg"], "videos": ["blob:https://twitter.com/68d2e363-3c20-4a4c-b3d5-498cde90cb5a"], "tweet_url": "https://twitter.com/alancarroII/status/1564391386857803778", "link": ""}, "1564384954678755328": {"tweet_id": "1564384954678755328", "username": "Kevin_Cage_", "name": "Kevin Cage", "profile_picture": "https://pbs.twimg.com/profile_images/1533868392729522178/F927yU8v_normal.png", "replies": 19, "retweets": 104, "likes": 417, "is_retweet": false, "posted_time": "2022-08-29T22:50:12+00:00", "content": "- Gensler meets Vanguard 7 times (they oversee his $120M fortune). Yet, ignores the #XRPCommunity \n\n- ~4.2% of Global Population or 320M people own crypto). Far less are \"using\" crypto. Wait for dApps to be the bedrock of centralized systems. Then BOOM\n\n- Typical #Ripple FUD", "hashtags": ["XRPCommunity", "Ripple"], "mentions": [], "images": [], "videos": [], "tweet_url": "https://twitter.com/Kevin_Cage_/status/1564384954678755328", "link": ""}, "1564382996517511169": {"tweet_id": "1564382996517511169", "username": "Yuto_gahagaha", "name": "Yuto Haga \u82b3\u8cc0 \u52c7\u4eba", "profile_picture": "https://pbs.twimg.com/profile_images/1497944428689956869/b2uHsb2P_normal.jpg", "replies": 0, "retweets": 47, "likes": 313, "is_retweet": false, "posted_time": "2022-08-29T22:42:25+00:00", "content": "JP\u30e2\u30eb\u30ac\u30f3\n\u300c\u30d0\u30ea\u30e5\u30fc\u682a\u306e\u30ed\u30f3\u30b0\u3001\u30d3\u30c3\u30c8\u30b3\u30a4\u30f3\u306e\u30b7\u30e7\u30fc\u30c8\u3092\u63a8\u5968\u300d\n\nJPMORGAN'S KELLY SAYS BUY VALUE, SELL CRYPTO WITH HAWKISH FED - BBG", "hashtags": [], "mentions": [], "images": [], "videos": [], "tweet_url": "https://twitter.com/Yuto_gahagaha/status/1564382996517511169", "link": ""}}