{"1397703147460628480": {"tweet_id": "1397703147460628480", "username": "RealChainGames", "name": "Chain Games", "profile_picture": "https://pbs.twimg.com/profile_images/1604755094305935361/PqUrTbYv_normal.jpg", "replies": 85, "retweets": 509, "likes": 1672, "is_retweet": true, "posted_time": "2021-05-26T23:56:13+00:00", "content": "Congrats \n@safemoon\n hodlers & community!\n\nWe will be creating a custom #SAFEMOON Crypto Kart and an exclusive #SAFEMOONARMY NFT that will be given away in a soon to be announced contest!\n\nCheck out https://github.com/Chain-Games/super-crypto-kart/releases/tag/2.3\u2026 for the latest Super Crypto Kart release!", "hashtags": ["SAFEMOON", "SAFEMOONARMY"], "mentions": ["safemoon"], "images": [], "videos": [], "tweet_url": "https://twitter.com/RealChainGames/status/1397703147460628480", "link": ""}, "1397700988249718788": {"tweet_id": "1397700988249718788", "username": "Gfilche", "name": "Gali", "profile_picture": "https://pbs.twimg.com/profile_images/1600589024208777216/W3Y7keqE_normal.jpg", "replies": 27, "retweets": 15, "likes": 234, "is_retweet": false, "posted_time": "2021-05-26T23:47:38+00:00", "content": "Yo \n@nic__carter\n this is an official invite to come on my podcast \n@HyperChangeTV\n !! bitcoin, energy consumption, doge, Tesla\u2019s future moves in the crypto markets, so much scheming to do!  $TSLA #Bitcoin", "hashtags": ["Bitcoin"], "mentions": ["nic__carter", "HyperChangeTV"], "images": [], "videos": [], "tweet_url": "https://twitter.com/Gfilche/status/1397700988249718788", "link": ""}, "1397700827024920580": {"tweet_id": "1397700827024920580", "username": "RyanSAdams", "name": "RYAN S\u039eAN ADAMS - rsa.eth", "profile_picture": "https://pbs.twimg.com/profile_images/1565052738983043078/BBqh_P_M_normal.jpg", "replies": 115, "retweets": 241, "likes": 2508, "is_retweet": false, "posted_time": "2021-05-26T23:46:59+00:00", "content": "Ethereum\u2019s layer 2 is going to hit crypto like a tidal wave  \n\nIt\u2019s gonna be a fun summer", "hashtags": [], "mentions": [], "images": [], "videos": [], "tweet_url": "https://twitter.com/RyanSAdams/status/1397700827024920580", "link": ""}, "1397694038267027463": {"tweet_id": "1397694038267027463", "username": "Cointelegraph", "name": "Cointelegraph", "profile_picture": "https://pbs.twimg.com/profile_images/1270073276740534274/APmUBHaI_normal.jpg", "replies": 13, "retweets": 75, "likes": 368, "is_retweet": false, "posted_time": "2021-05-26T23:20:01+00:00", "content": "As reliance on cash declines, \n@PayPal\n doubles down on crypto. Soon users will be able to withdraw their digital assets from the platform and move to other wallets. How does this benefit you as a consumer? https://buff.ly/2RNLTCW", "hashtags": [], "mentions": ["PayPal"], "images": [], "videos": [], "tweet_url": "https://twitter.com/Cointelegraph/status/1397694038267027463", "link": ""}, "1397693596212494337": {"tweet_id": "1397693596212494337", "username": "CoinbaseNews", "name": "Coinbase News", "profile_picture": "https://pbs.twimg.com/profile_images/1389269447777476610/Q1uTnwQ9_normal.png", "replies": 74, "retweets": 152, "likes": 449, "is_retweet": false, "posted_time": "2021-05-26T23:18:15+00:00", "content": "There\u2019s a lot of false info about crypto out there. It\u2019s time to address it \u2026 with truth. Announcing Coinbase Fact Check, a new effort to combat myths and misinformation as people enter the crypto economy.\n\nLearn more here \u2193", "hashtags": [], "mentions": [], "images": [], "videos": [], "tweet_url": "https://twitter.com/CoinbaseNews/status/1397693596212494337", "link": "https://t.co/3AOCoEENtV"}, "1397692007582162944": {"tweet_id": "1397692007582162944", "username": "IvanOnTech", "name": "Ivan on Tech - Building Moralis Web3", "profile_picture": "https://pbs.twimg.com/profile_images/1518973700477014019/uvn24DNS_normal.jpg", "replies": 50, "retweets": 45, "likes": 856, "is_retweet": false, "posted_time": "2021-05-26T23:11:57+00:00", "content": "Crypto programming is magic ", "hashtags": [], "mentions": [], "images": [], "videos": [], "tweet_url": "https://twitter.com/IvanOnTech/status/1397692007582162944", "link": ""}, "1397689557714341889": {"tweet_id": "1397689557714341889", "username": "punk4156", "name": "4156", "profile_picture": "https://pbs.twimg.com/profile_images/1615752376245166080/VA4ceDGH_normal.jpg", "replies": 21, "retweets": 45, "likes": 384, "is_retweet": false, "posted_time": "2021-05-26T23:02:13+00:00", "content": "crypto survival guide, rule #1: however early you think it is, it\u2019s earlier still", "hashtags": ["1"], "mentions": [], "images": [], "videos": [], "tweet_url": "https://twitter.com/punk4156/status/1397689557714341889", "link": ""}, "1397688288534687747": {"tweet_id": "1397688288534687747", "username": "TheCryptoLark", "name": "Lark Davis", "profile_picture": "https://pbs.twimg.com/profile_images/1482889740223680514/jWHeNCpH_normal.png", "replies": 61, "retweets": 67, "likes": 758, "is_retweet": false, "posted_time": "2021-05-26T22:57:10+00:00", "content": "Learning how to click on the sell button is perhaps one of the most important skills a new investor can master. \n\nSell on market pumps when everyone is mega mega bullish, posting pictures of cars and watches, and screaming new paradigm of money. \n\n#crypto", "hashtags": ["crypto"], "mentions": [], "images": [], "videos": [], "tweet_url": "https://twitter.com/TheCryptoLark/status/1397688288534687747", "link": ""}, "1397687036434321408": {"tweet_id": "1397687036434321408", "username": "StockLizardKing", "name": "lizard", "profile_picture": "https://pbs.twimg.com/profile_images/1619850304983277570/oNvVoE9i_normal.jpg", "replies": 25, "retweets": 155, "likes": 196, "is_retweet": false, "posted_time": "2021-05-26T22:52:11+00:00", "content": "RT this if you own crypto\n\nComment \u201cI enjoy being poor\u201d if you don\u2019t", "hashtags": [], "mentions": [], "images": [], "videos": [], "tweet_url": "https://twitter.com/StockLizardKing/status/1397687036434321408", "link": ""}, "1397686533927358469": {"tweet_id": "1397686533927358469", "username": "TateBerenbaum", "name": "t8.arweave.dev", "profile_picture": "https://pbs.twimg.com/profile_images/1480328078916161540/oo8QcpAY_normal.jpg", "replies": 19, "retweets": 10, "likes": 161, "is_retweet": false, "posted_time": "2021-05-26T22:50:12+00:00", "content": "Finished my last exam for high school today.\n\nPumped to finally be able to pursue \n@vertoexchange\n full time! \n\nHigh school  Crypto metaverse", "hashtags": [], "mentions": ["vertoexchange"], "images": [], "videos": [], "tweet_url": "https://twitter.com/TateBerenbaum/status/1397686533927358469", "link": ""}}