{"1350593645871837185": {"tweet_id": "1350593645871837185", "username": "MFbtc", "name": "MF", "profile_picture": "https://pbs.twimg.com/profile_images/1612540397779034128/x3Se7wYM_normal.jpg", "replies": 1, "retweets": 1, "likes": 6, "is_retweet": false, "posted_time": "2021-01-16T23:59:52+00:00", "content": "@CryptoRadio\n @Witty_Crypto\n @sabotagebeats\n @nflux1\n @empty_banks\n @brandonittus\n @Ezca3\n @enkitunes\n @d0c0il3rhodls @bitcoinjacket \n@CryptoMedra\n @pickingtrades\n @nixops\n @SoundDrGenie\n @Sleep3zz\n @JoshMcGruff\n @RickDLewis1\n @dvharry2020\n @namaste_nic\n @LiquidLiveclub", "hashtags": [], "mentions": ["CryptoRadio", "Witty_Crypto", "sabotagebeats", "nflux1", "empty_banks", "brandonittus", "Ezca3", "enkitunes", "d0c0il3rhodls", "bitcoinjacket", "CryptoMedra", "pickingtrades", "nixops", "SoundDrGenie", "Sleep3zz", "JoshMcGruff", "RickDLewis1", "dvharry2020", "namaste_nic", "LiquidLiveclub"], "images": [], "videos": [], "tweet_url": "https://twitter.com/MFbtc/status/1350593645871837185", "link": ""}, "1350593603341611009": {"tweet_id": "1350593603341611009", "username": "MFbtc", "name": "MF", "profile_picture": "https://pbs.twimg.com/profile_images/1612540397779034128/x3Se7wYM_normal.jpg", "replies": 1, "retweets": 5, "likes": 8, "is_retweet": false, "posted_time": "2021-01-16T23:59:42+00:00", "content": "Going live 8pm eastern! Regular crypto radio and also on twitch! https://twitch.tv/liquidliveclub", "hashtags": [], "mentions": [], "images": [], "videos": [], "tweet_url": "https://twitter.com/MFbtc/status/1350593603341611009", "link": ""}, "1350593579748626436": {"tweet_id": "1350593579748626436", "username": "QuattroCinco369", "name": "QuattroCinco", "profile_picture": "https://pbs.twimg.com/profile_images/1274892973843628033/tSuwPUdD_normal.jpg", "replies": 5, "retweets": 0, "likes": 17, "is_retweet": false, "posted_time": "2021-01-16T23:59:36+00:00", "content": "I prefer to avoid the counter party risk by giving someone else my keys. Also why take a paltry return of 6% when you know Blockfi is keeping the rest. There are alternatives like #HEX which pay 30-60% APY when you stake. Crypto was designed to get rid of middlemen.", "hashtags": ["HEX"], "mentions": [], "images": [], "videos": [], "tweet_url": "https://twitter.com/QuattroCinco369/status/1350593579748626436", "link": ""}, "1350593200872845313": {"tweet_id": "1350593200872845313", "username": "NTmoney", "name": "Nick Tomaino", "profile_picture": "https://pbs.twimg.com/profile_images/1621269343672877056/Qzm_uALg_normal.jpg", "replies": 0, "retweets": 2, "likes": 9, "is_retweet": false, "posted_time": "2021-01-16T23:58:06+00:00", "content": "Crypto twitter might have some fun with \n@pinatafarms\n ", "hashtags": [], "mentions": ["pinatafarms"], "images": ["https://pbs.twimg.com/ext_tw_video_thumb/1350593181126049792/pu/img/Q8rm0inawj7vg_IF.jpg"], "videos": ["blob:https://twitter.com/b420af6b-1619-4d28-8793-b515aefa478c"], "tweet_url": "https://twitter.com/NTmoney/status/1350593200872845313", "link": ""}, "1350593038502998016": {"tweet_id": "1350593038502998016", "username": "NathanMars7", "name": "NathanMars", "profile_picture": "https://pbs.twimg.com/profile_images/1373406432566120458/zCt-pOWQ_normal.jpg", "replies": 1, "retweets": 7, "likes": 31, "is_retweet": true, "posted_time": "2021-01-16T23:57:27+00:00", "content": "There is no other Crypto community like $LEO and $HIVE", "hashtags": [], "mentions": [], "images": ["https://pbs.twimg.com/media/Er3HlhSXIAQftCz?format=jpg&name=small"], "videos": [], "tweet_url": "https://twitter.com/NathanMars7/status/1350593038502998016", "link": ""}}