{"1480690798236557312": {"tweet_id": "1480690798236557312", "username": "TheDazzleNovak", "name": "\u20bfrandon", "profile_picture": "https://pbs.twimg.com/profile_images/1505575332669116416/xih0Weq__normal.jpg", "replies": 0, "retweets": 4, "likes": 16, "is_retweet": false, "posted_time": "2022-01-10T23:59:30+00:00", "content": "@cobie\n bring \n@aaronmcdnz\n on Up Only tv to talk \n@FLUF_World\n and \n@altstatemachine\n! Would be awesome!", "hashtags": [], "mentions": ["cobie", "aaronmcdnz", "FLUF_World", "altstatemachine"], "images": [], "videos": [], "tweet_url": "https://twitter.com/TheDazzleNovak/status/1480690798236557312", "link": ""}, "1480690736718880770": {"tweet_id": "1480690736718880770", "username": "jesse_nft", "name": "yahboidad.eth", "profile_picture": "https://pbs.twimg.com/profile_images/1596910294621687809/rHO0iUhh_normal.png", "replies": 9, "retweets": 12, "likes": 53, "is_retweet": false, "posted_time": "2022-01-10T23:59:16+00:00", "content": "Where my \n@EnigmaECONOMY\n fam???? #enigmaeconomy scooped this man off the floor, great entry point for crypto mining operation. Many whales slowly accumulating, floor on v1 and v2 are .4ish. Dyor NFA have fun and print ", "hashtags": ["enigmaeconomy"], "mentions": ["EnigmaECONOMY"], "images": ["https://pbs.twimg.com/media/FIx4YGYXoAct04S?format=jpg&name=small"], "videos": [], "tweet_url": "https://twitter.com/jesse_nft/status/1480690736718880770", "link": ""}, "1480690650911760384": {"tweet_id": "1480690650911760384", "username": "beaniemaxi", "name": "Beanie", "profile_picture": "https://pbs.twimg.com/profile_images/1493937713657040904/Wzxv1_us_normal.jpg", "replies": 38, "retweets": 21, "likes": 448, "is_retweet": false, "posted_time": "2022-01-10T23:58:55+00:00", "content": "I\u2019m more bullish on NFT technology than anything else. I own a lot of crypto mostly ETH. And I have a very nice NFT portfolio. But what excites me most about these early days are the SAFTs I\u2019m signing. I\u2019m pretty much going all in on venture rn. Funded several new startups today.", "hashtags": [], "mentions": [], "images": [], "videos": [], "tweet_url": "https://twitter.com/beaniemaxi/status/1480690650911760384", "link": ""}, "1480690648391036930": {"tweet_id": "1480690648391036930", "username": "Neolawyer1", "name": "NEO", "profile_picture": "https://pbs.twimg.com/profile_images/1559736876189290497/4KDgoim2_normal.jpg", "replies": 8, "retweets": 7, "likes": 38, "is_retweet": false, "posted_time": "2022-01-10T23:58:55+00:00", "content": "From August 2020 to date, $EWT has down from 50th to 228th in the crypto rankings (marketcap).\n\nThat must be change and soon it will.", "hashtags": [], "mentions": [], "images": [], "videos": [], "tweet_url": "https://twitter.com/Neolawyer1/status/1480690648391036930", "link": ""}, "1480690644729298947": {"tweet_id": "1480690644729298947", "username": "CryptoInColor", "name": "Crypto In Color", "profile_picture": "https://pbs.twimg.com/profile_images/1440207639443505160/NddGwXff_normal.jpg", "replies": 4, "retweets": 1, "likes": 23, "is_retweet": false, "posted_time": "2022-01-10T23:58:54+00:00", "content": "The daily candles are about to close! Watch for any volatile movement! BTC is a hair under green before closing. Huge volume all over the crypto market today! \n\nI\u2019m bullish  2022 is in", "hashtags": [], "mentions": [], "images": [], "videos": [], "tweet_url": "https://twitter.com/CryptoInColor/status/1480690644729298947", "link": ""}, "1480690560109359108": {"tweet_id": "1480690560109359108", "username": "DeFiChick", "name": "natalie", "profile_picture": "https://pbs.twimg.com/profile_images/1505359488504655874/WZM7ojlw_normal.png", "replies": 5, "retweets": 4, "likes": 79, "is_retweet": false, "posted_time": "2022-01-10T23:58:34+00:00", "content": "gn crypto world, lovers and friends! \n@reachlang\n shirt works for every occassion!  I\u2019ll be dreamin\u2019 about \n@PrismaticFi\n and \n@Algorand\n!  WAGMI ", "hashtags": [], "mentions": ["reachlang", "PrismaticFi", "Algorand"], "images": ["https://pbs.twimg.com/media/FIx4NuVXoAU8umq?format=jpg&name=900x900"], "videos": [], "tweet_url": "https://twitter.com/DeFiChick/status/1480690560109359108", "link": ""}}