{"1566213504444538880": {"tweet_id": "1566213504444538880", "username": "themetav3rse", "name": "Metav3rse", "profile_picture": "https://pbs.twimg.com/profile_images/1514431103372779522/uXyv4umu_normal.jpg", "replies": 12, "retweets": 13, "likes": 147, "is_retweet": false, "posted_time": "2022-09-03T23:56:12+00:00", "content": "Vitalik Buterin says that price crashes like Terra's are healthy for the crypto ecosystem because it \"exposes unsustainable business models\".\n\nWhat other projects/coins come to mind when you hear this?", "hashtags": [], "mentions": [], "images": [], "videos": [], "tweet_url": "https://twitter.com/themetav3rse/status/1566213504444538880", "link": ""}, "1566209639930368001": {"tweet_id": "1566209639930368001", "username": "0xdoug", "name": "Doug Colkitt (,)", "profile_picture": "https://pbs.twimg.com/profile_images/1602305311825698816/neVOjVu9_normal.jpg", "replies": 22, "retweets": 14, "likes": 167, "is_retweet": false, "posted_time": "2022-09-03T23:40:51+00:00", "content": "The most bearish sign for crypto right now is that there\u2019s no demand for blockspace on a Saturday afternoon. \n\nThat\u2019s a sign that apps need to do a better job driving organic retail engagement. TikTok has no trouble competing with college football.", "hashtags": [], "mentions": [], "images": ["https://pbs.twimg.com/media/FbxLXdMXEAA0H4C?format=jpg&name=360x360"], "videos": [], "tweet_url": "https://twitter.com/0xdoug/status/1566209639930368001", "link": ""}, "1566202780020269056": {"tweet_id": "1566202780020269056", "username": "Amooor1st", "name": "Amr.grv", "profile_picture": "https://pbs.twimg.com/profile_images/1589342421317550083/vz4oD9Nx_normal.jpg", "replies": 12, "retweets": 102, "likes": 250, "is_retweet": false, "posted_time": "2022-09-03T23:13:36+00:00", "content": "- We are in talks with big exchanges \n- Bridge DONE. Only final test\n- Grove Keeper Wallet ( Soon ) \n- Dubai Crypto Expo ( October ) \n@Rawoof_LJ\n @Winterradler\n @Simonspiteri22\n @Sk280488\n @JohnGh87", "hashtags": [], "mentions": ["Rawoof_LJ", "Winterradler", "Simonspiteri22", "Sk280488", "JohnGh87"], "images": ["https://pbs.twimg.com/ext_tw_video_thumb/1566202466278035463/pu/img/vf2dzMgYZIluHJbY.jpg"], "videos": ["blob:https://twitter.com/8387197f-3919-4386-b3ca-5963126cd2f2"], "tweet_url": "https://twitter.com/Amooor1st/status/1566202780020269056", "link": ""}, "1566196362059943936": {"tweet_id": "1566196362059943936", "username": "TorayKortan", "name": "T", "profile_picture": "https://pbs.twimg.com/profile_images/1570155452264071171/Tdm6hBR1_normal.jpg", "replies": 19, "retweets": 63, "likes": 292, "is_retweet": false, "posted_time": "2022-09-03T22:48:05+00:00", "content": "People often ask me \u201cwhy do you not talk about the future of crypto so much\u201d\n\nBecause I done my research a long time ago, and continue to do so as time passes.\n\nMy understanding of this field and how it ties into the bigger picture goes beyond moons and rocket ships.", "hashtags": [], "mentions": [], "images": ["https://pbs.twimg.com/media/Fbw_Sg5XEAMtuSi?format=jpg&name=small", "https://pbs.twimg.com/media/Fbw_Sg4XEAIp_Ks?format=jpg&name=small", "https://pbs.twimg.com/media/Fbw_Sg5WQAEHguJ?format=jpg&name=small", "https://pbs.twimg.com/media/Fbw_Sg5XkAAMdd0?format=jpg&name=small"], "videos": [], "tweet_url": "https://twitter.com/TorayKortan/status/1566196362059943936", "link": ""}, "1566196178014072832": {"tweet_id": "1566196178014072832", "username": "YoungMilkmanNft", "name": "0069.eth", "profile_picture": "https://pbs.twimg.com/profile_images/1557907914765250560/BI1yW73U_normal.jpg", "replies": 43, "retweets": 14, "likes": 204, "is_retweet": false, "posted_time": "2022-09-03T22:47:22+00:00", "content": "How many of y\u2019all went stocks to crypto to NFT\u2019s and have never looked back at stocks.", "hashtags": [], "mentions": [], "images": [], "videos": [], "tweet_url": "https://twitter.com/YoungMilkmanNft/status/1566196178014072832", "link": ""}, "1566182497293058048": {"tweet_id": "1566182497293058048", "username": "CryptoWendyO", "name": "Wendy O", "profile_picture": "https://pbs.twimg.com/profile_images/1558666143648210944/YpbjdhuQ_normal.jpg", "replies": 98, "retweets": 6, "likes": 237, "is_retweet": false, "posted_time": "2022-09-03T21:53:00+00:00", "content": "I have never really had friends irl, but after joining crypto twitter i am proud to announce.....\n\ni finally was able to make friends!\n\n59204057450947508 bots!", "hashtags": [], "mentions": [], "images": ["https://pbs.twimg.com/media/FbwJKOMVUAAbXYk?format=jpg&name=small"], "videos": [], "tweet_url": "https://twitter.com/CryptoWendyO/status/1566182497293058048", "link": ""}}