{"1504608426764161028": {"tweet_id": "1504608426764161028", "username": "DACsalesbot", "name": "Degen Ape Club SALES", "profile_picture": "https://pbs.twimg.com/profile_images/1487758456740265984/yk1MWhRs_normal.jpg", "replies": 1, "retweets": 2, "likes": 17, "is_retweet": false, "posted_time": "2022-03-17T23:59:37+00:00", "content": " DegenApe #1962 has been bought for 0.45 BNB ($176 USD)\n\nRank: 1710\n\n #nfts #bnb #bsc #crypto #DegenApeClub #BAYC", "hashtags": ["1962", "nfts", "bnb", "bsc", "crypto", "DegenApeClub", "BAYC"], "mentions": [], "images": ["https://pbs.twimg.com/media/FOFxZBbXMAMGxd-?format=png&name=small"], "videos": [], "tweet_url": "https://twitter.com/DACsalesbot/status/1504608426764161028", "link": ""}, "1504608283511955468": {"tweet_id": "1504608283511955468", "username": "magdalenakala", "name": "mags.eth phoenix", "profile_picture": "https://pbs.twimg.com/profile_images/1502693195234304002/vE350uvP_normal.jpg", "replies": 0, "retweets": 0, "likes": 10, "is_retweet": false, "posted_time": "2022-03-17T23:59:03+00:00", "content": "when I first got into crypto, someone told me: \n\n\"there are no hot men in crypto, there are only hot women in crypto\" ", "hashtags": [], "mentions": [], "images": [], "videos": [], "tweet_url": "https://twitter.com/magdalenakala/status/1504608283511955468", "link": ""}, "1504608281074970624": {"tweet_id": "1504608281074970624", "username": "btc", "name": "BTC Times", "profile_picture": "https://pbs.twimg.com/profile_images/1292159368943693824/JXYCQur0_normal.jpg", "replies": 9, "retweets": 21, "likes": 84, "is_retweet": false, "posted_time": "2022-03-17T23:59:03+00:00", "content": "SEC comes under fire from Congress for behavior towards #bitcoin and #crypto companies.", "hashtags": ["bitcoin", "crypto"], "mentions": [], "images": [], "videos": [], "tweet_url": "https://twitter.com/btc/status/1504608281074970624", "link": "https://t.co/Bn3tgeMXGp"}, "1504608024039763970": {"tweet_id": "1504608024039763970", "username": "Crypto_God_Jay", "name": "Crypto God", "profile_picture": "https://pbs.twimg.com/profile_images/1518674545963671554/BDyN2uQ9_normal.jpg", "replies": 2, "retweets": 0, "likes": 12, "is_retweet": false, "posted_time": "2022-03-17T23:58:01+00:00", "content": "Learning to take profits when you should is how you become a winner in the crypto space don\u2019t get left with your hands around your balls on a cold winter night ", "hashtags": [], "mentions": [], "images": [], "videos": [], "tweet_url": "https://twitter.com/Crypto_God_Jay/status/1504608024039763970", "link": ""}, "1504607926408818697": {"tweet_id": "1504607926408818697", "username": "Theblondejon", "name": "Blondejon", "profile_picture": "https://pbs.twimg.com/profile_images/1543376858711859200/y7EjBw1E_normal.jpg", "replies": 4, "retweets": 4, "likes": 17, "is_retweet": false, "posted_time": "2022-03-17T23:57:38+00:00", "content": "Snapchat hit me up & they want to do a Snapchat show with me. I told them I rather just get airdropped Crypto Punk #3536 instead of USD\u2026 Hopefully they budge ", "hashtags": ["3536"], "mentions": [], "images": [], "videos": [], "tweet_url": "https://twitter.com/Theblondejon/status/1504607926408818697", "link": ""}, "1504607914757042186": {"tweet_id": "1504607914757042186", "username": "CL207", "name": "CL", "profile_picture": "https://pbs.twimg.com/profile_images/1611974993734434817/t7Kmqs43_normal.jpg", "replies": 1, "retweets": 0, "likes": 19, "is_retweet": false, "posted_time": "2022-03-17T23:57:35+00:00", "content": "sometime ago, some straight A finance student in my school was telling me how he think crypto down, btc 0 soon (literally 0), and how he is bullish x y and z stocks\n\nnext week, he post on facebook how he lost majority of his nw and struggling super hard", "hashtags": [], "mentions": [], "images": [], "videos": [], "tweet_url": "https://twitter.com/CL207/status/1504607914757042186", "link": ""}, "1504607890895745025": {"tweet_id": "1504607890895745025", "username": "JBM_Ultra", "name": "JBM | \u156b", "profile_picture": "https://pbs.twimg.com/profile_images/1522639473980448770/amOS3IGF_normal.jpg", "replies": 4, "retweets": 2, "likes": 60, "is_retweet": false, "posted_time": "2022-03-17T23:57:30+00:00", "content": "In pratically 3 years in crypto, before I realize how big $UOS was, I always met people that was calling projects I was in like shitcoins, scams, etc. Fudders. \n\nI can\u2019t see FuD on $UOS. No one\u2019s to fight with. \nThe only negativity I find is like \u00ab it\u2019s slow wen live \u00bb", "hashtags": [], "mentions": [], "images": [], "videos": [], "tweet_url": "https://twitter.com/JBM_Ultra/status/1504607890895745025", "link": ""}, "1504607322101985285": {"tweet_id": "1504607322101985285", "username": "bocagrandiart", "name": "BocaGrandi Art NFT.NYC 2023", "profile_picture": "https://pbs.twimg.com/profile_images/1624459390949691393/PAkTOU0L_normal.jpg", "replies": 1, "retweets": 5, "likes": 14, "is_retweet": false, "posted_time": "2022-03-17T23:55:14+00:00", "content": "Recently minted \u201cToxic  Red Moon & Specter \u201d to my Caribbean Toxic Collection  Check out on : https://opensea.io/Bocagrandiart #opensea #NFTs #Ethereum #crypto #NFTCommunity #NFTgoodvibes #NFTartists", "hashtags": ["opensea", "NFTs", "Ethereum", "crypto", "NFTCommunity", "NFTgoodvibes", "NFTartists"], "mentions": [], "images": ["https://pbs.twimg.com/media/FOFwYVtVsBUaerB?format=jpg&name=small"], "videos": [], "tweet_url": "https://twitter.com/bocagrandiart/status/1504607322101985285", "link": ""}}