{"1404226346251739136": {"tweet_id": "1404226346251739136", "username": "max_bronstein", "name": "Max Bronstein", "profile_picture": "https://pbs.twimg.com/profile_images/1519450845196267524/5kudHiH8_normal.jpg", "replies": 0, "retweets": 2, "likes": 67, "is_retweet": false, "posted_time": "2021-06-13T23:57:04+00:00", "content": "The belief that future cycles will be different is simple:\n\n\u2022 Never before has there been 1) this much liquidity in the world and 2) this many eyes on the crypto-economy\n\n\u2022 Maturing market structure has made it easier to harvest volatility and express financial views", "hashtags": [], "mentions": [], "images": [], "videos": [], "tweet_url": "https://twitter.com/max_bronstein/status/1404226346251739136", "link": ""}, "1404226199476375555": {"tweet_id": "1404226199476375555", "username": "JonhnyAguilar", "name": "Johnny \u2b23 HEX\u2075\u2075\u2075\u2075", "profile_picture": "https://pbs.twimg.com/profile_images/1378893706544173058/ZC8EgL0h_normal.jpg", "replies": 4, "retweets": 1, "likes": 40, "is_retweet": false, "posted_time": "2021-06-13T23:56:29+00:00", "content": "I followed \n@Hexologist31\nHEXample. Buying #Pizza with #Crypto is a great way to on board people. \n\nHe thanks me for introducing him to #HEX and I THANK YOU \n@RichardHeartWin\n for creating $HEX and also a BIG THANK YOU to all the #HEXICANS that keep spreading the good word. ", "hashtags": ["Pizza", "Crypto", "HEX", "HEXICANS"], "mentions": ["Hexologist31", "RichardHeartWin"], "images": ["https://pbs.twimg.com/media/E3zQSRmXwAIbvjt?format=jpg&name=900x900"], "videos": [], "tweet_url": "https://twitter.com/JonhnyAguilar/status/1404226199476375555", "link": ""}, "1404226006551085057": {"tweet_id": "1404226006551085057", "username": "TESLAcharts", "name": "TC", "profile_picture": "https://pbs.twimg.com/profile_images/1395055434306887680/7wlYkt2p_normal.jpg", "replies": 5, "retweets": 20, "likes": 120, "is_retweet": false, "posted_time": "2021-06-13T23:55:43+00:00", "content": "The price of bitcoin should be quoted in tethers, not USD. It\u2019s not traded in USD. You can\u2019t exit the crypto universe with USD in size. The current price of bitcoin is about 39,000 tethers. Getting people to quote it in USD is key to the con.", "hashtags": [], "mentions": [], "images": [], "videos": [], "tweet_url": "https://twitter.com/TESLAcharts/status/1404226006551085057", "link": ""}, "1404225810236588033": {"tweet_id": "1404225810236588033", "username": "MarathonDH", "name": "Marathon Digital Holdings (NASDAQ: MARA)", "profile_picture": "https://pbs.twimg.com/profile_images/1552713854932623360/_pc9SWUM_normal.jpg", "replies": 2, "retweets": 9, "likes": 75, "is_retweet": false, "posted_time": "2021-06-13T23:54:57+00:00", "content": "$MARA #Bitcoin \n@fgthiel\n, CEO of Marathon Digital Holdings, in the latest edition of Thinking Crypto\u2019 stated:\n\n\u201cBTC mining industry has already made great progress towards carbon neutrality.\u201d", "hashtags": ["Bitcoin"], "mentions": ["fgthiel"], "images": [], "videos": [], "tweet_url": "https://twitter.com/MarathonDH/status/1404225810236588033", "link": "https://t.co/9rgHQdhD7V"}, "1404225622688342019": {"tweet_id": "1404225622688342019", "username": "BitBruceWayne", "name": "\u20bfRUC\u039e WA\u00a5N\u039e", "profile_picture": "https://pbs.twimg.com/profile_images/1603918586094952448/XYmzd0vM_normal.jpg", "replies": 1, "retweets": 3, "likes": 24, "is_retweet": false, "posted_time": "2021-06-13T23:54:12+00:00", "content": "The 24hr volume in crypto is up $120bn today. \nThat's more than the WHOLE crypto market at some points during 2019.\nIn 24 hours. ", "hashtags": [], "mentions": [], "images": [], "videos": [], "tweet_url": "https://twitter.com/BitBruceWayne/status/1404225622688342019", "link": ""}, "1404224621323296772": {"tweet_id": "1404224621323296772", "username": "LeVagabondeNFT", "name": "Le Vagabonde NFT", "profile_picture": "https://pbs.twimg.com/profile_images/1575545220540035072/R2j6HE3p_normal.jpg", "replies": 0, "retweets": 8, "likes": 18, "is_retweet": true, "posted_time": "2021-06-13T23:50:13+00:00", "content": "Hey big hitters, please share this on your channels for the growth of WAX.. all tides rise together! \n@Bitboy_Crypto\n @CryptoStache\n @KennethBosak\n @bennydoda01\n @BonzManifest\n @mBluCrypto\n @ColonizeMarsNFT", "hashtags": [], "mentions": ["Bitboy_Crypto", "CryptoStache", "KennethBosak", "bennydoda01", "BonzManifest", "mBluCrypto", "ColonizeMarsNFT"], "images": [], "videos": [], "tweet_url": "https://twitter.com/LeVagabondeNFT/status/1404224621323296772", "link": ""}, "1404224397007859717": {"tweet_id": "1404224397007859717", "username": "dcherring", "name": "Dennis Herring", "profile_picture": "https://pbs.twimg.com/profile_images/1303721964935081985/vLolZwVm_normal.jpg", "replies": 3, "retweets": 0, "likes": 26, "is_retweet": false, "posted_time": "2021-06-13T23:49:20+00:00", "content": "I\u2019d lay a little crypto on *BS*.", "hashtags": [], "mentions": [], "images": [], "videos": [], "tweet_url": "https://twitter.com/dcherring/status/1404224397007859717", "link": ""}}